{"cameraMode":{"drawMode":0,"name":"Shaded","section":"Shading Mode"},"sceneLighting":true,"audioPlay":false,"sceneViewState":{"m_AlwaysRefresh":false,"showFog":true,"showSkybox":true,"showFlares":true,"showImageEffects":true,"showParticleSystems":true,"showVisualEffectGraphs":true,"m_FxEnabled":false},"in2DMode":false,"pivot":{"x":-8.887160301208496,"y":-2.483947515487671,"z":-1.2391297817230225},"rotation":{"x":-0.09179645031690598,"y":0.670215904712677,"z":-0.08408496528863907,"w":-0.731658399105072},"size":13.095230102539063,"orthographic":false}